AFHscraper.py
androidfilehostscraper-3.0.0.dist-info/licenses/LICENSE
androidfilehostscraper-3.0.0.dist-info/METADATA
androidfilehostscraper-3.0.0.dist-info/WHEEL
androidfilehostscraper-3.0.0.dist-info/entry_points.txt
androidfilehostscraper-3.0.0.dist-info/top_level.txt
androidfilehostscraper-3.0.0.dist-info/RECORD
