Metadata-Version: 2.4
Name: AndroidFileHostScraper
Version: 3.0.0
Summary: Simple and powerful Python script to download files from AndroidFileHost by imitating their API calls.
Author-email: codefl0w <fl0w_dev@protonmail.com>
License: Apache-2.0
Project-URL: Homepage, https://github.com/codefl0w/AndroidFileHostScraper
Project-URL: Repository, https://github.com/codefl0w/AndroidFileHostScraper
Project-URL: Issues, https://github.com/codefl0w/AndroidFileHostScraper/issues
Project-URL: Donate, https://buymeacoffee.com/fl0w
Requires-Python: >=3.8
License-File: LICENSE
Requires-Dist: httpx>=0.25.2
Requires-Dist: h2>=4.1.0
Requires-Dist: beautifulsoup4>=4.12.3
Dynamic: license-file
